folderbrowser/__init__.py
folderbrowser/__main__.py
folderbrowser/server.py
poetry.lock
folderbrowser-0.1.4.dist-info/LICENSE.txt
folderbrowser-0.1.4.dist-info/WHEEL
folderbrowser-0.1.4.dist-info/METADATA
folderbrowser-0.1.4.dist-info/RECORD
