Metadata-Version: 2.1
Name: folderbrowser
Version: 0.1.4
Summary: Lightweight webserver to browse folder and its contents on a webbrowser
Home-page: https://github.com/wbjrpub/folderbrowser
License: MIT
Keywords: folder,directory,webserver
Author: Wouter Batelaan
Author-email: wbjrpub@gmail.com
Requires-Python: >=3.6
Classifier: Development Status :: 4 - Beta
Classifier: Environment :: Web Environment
Classifier: Intended Audience :: Developers
Classifier: Intended Audience :: End Users/Desktop
Classifier: License :: OSI Approved :: MIT License
Classifier: Natural Language :: English
Classifier: Programming Language :: Python :: 3
Classifier: Programming Language :: Python :: 3.6
Classifier: Programming Language :: Python :: 3.7
Classifier: Programming Language :: Python :: 3.8
Classifier: Programming Language :: Python :: 3.9
Classifier: Topic :: Internet :: WWW/HTTP :: Browsers
Classifier: Topic :: Internet :: WWW/HTTP :: HTTP Servers
Project-URL: Repository, https://github.com/wbjrpub/folderbrowser
